nviz/__init__.py
nviz/_version.py
nviz/cli.py
nviz/image.py
nviz/image_meta.py
nviz/report.py
nviz/view.py
nviz-0.0.4.dist-info/licenses/LICENSE
nviz-0.0.4.dist-info/METADATA
nviz-0.0.4.dist-info/WHEEL
nviz-0.0.4.dist-info/entry_points.txt
nviz-0.0.4.dist-info/top_level.txt
nviz-0.0.4.dist-info/RECORD
