Metadata-Version: 2.4
Name: nviz
Version: 0.0.4
Summary: A tool for creating and visualizing n-dimensional microscopy images.
Classifier: Programming Language :: Python :: 3 :: Only
Classifier: Programming Language :: Python :: 3.11
Classifier: Programming Language :: Python :: 3.12
Classifier: Programming Language :: Python :: 3.13
Requires-Python: >=3.11
License-File: LICENSE
Requires-Dist: fire>=0.7
Requires-Dist: napari[all]>=0.5.5
Requires-Dist: napari-ome-zarr>=0.6.1
Requires-Dist: numpy<2.4
Requires-Dist: ome-zarr>=0.10.2
Requires-Dist: tifffile>=2024.12.12
Requires-Dist: xmltodict>=0.14.2
Requires-Dist: zarr>=2.18.4
Dynamic: license-file
